pygfried.h
pygfried.pyd
pygfried/__init__.pyi
pygfried/py.typed
pygfried-0.12.0.dist-info/licenses/LICENSE
pygfried-0.12.0.dist-info/METADATA
pygfried-0.12.0.dist-info/WHEEL
pygfried-0.12.0.dist-info/top_level.txt
pygfried-0.12.0.dist-info/RECORD
