Metadata-Version: 2.4
Name: pygfried
Version: 0.12.0
Summary: Siegfried as a Python extension
Home-page: https://github.com/artefactual-labs/pygfried
Author: Artefactual Systems Inc.
Author-email: info@artefactual.com
License: Apache 2.0
Classifier: Development Status :: 3 - Alpha
Classifier: Programming Language :: Python :: 3
Classifier: Programming Language :: Python :: 3 :: Only
Classifier: Programming Language :: Python :: 3.9
Classifier: Programming Language :: Python :: 3.10
Classifier: Programming Language :: Python :: 3.11
Classifier: Programming Language :: Python :: 3.12
Classifier: Programming Language :: Python :: 3.13
Classifier: Programming Language :: Python :: Implementation :: CPython
Requires-Python: >=3.9
License-File: LICENSE
Dynamic: license-file
